{
  "id": "book2unit3",
  "name": "Book2 Unit 3",
  "description": "衣物",
  "words": [
    {
      "word": "so",
      "phonetic": "",
      "meaning": "这么，如此"
    },
    {
      "word": "cool",
      "phonetic": "",
      "meaning": "酷的"
    },
    {
      "word": "clothes",
      "phonetic": "",
      "meaning": "衣服"
    },
    {
      "word": "wear",
      "phonetic": "",
      "meaning": "穿"
    },
    {
      "word": "cap",
      "phonetic": "",
      "meaning": "（有帽舌的）帽子"
    },
    {
      "word": "T-shirt",
      "phonetic": "",
      "meaning": "T恤"
    },
    {
      "word": "trousers",
      "phonetic": "",
      "meaning": "裤子"
    },
    {
      "word": "sock",
      "phonetic": "",
      "meaning": "袜子"
    },
    {
      "word": "shiny",
      "phonetic": "",
      "meaning": "闪光的"
    },
    {
      "word": "shoe",
      "phonetic": "",
      "meaning": "鞋"
    },
    {
      "word": "dress",
      "phonetic": "",
      "meaning": "连衣裙"
    },
    {
      "word": "sweater",
      "phonetic": "",
      "meaning": "毛衣"
    },
    {
      "word": "skirt",
      "phonetic": "",
      "meaning": "裙子"
    },
    {
      "word": "shirt",
      "phonetic": "",
      "meaning": "衬衫"
    },
    {
      "word": "coat",
      "phonetic": "",
      "meaning": "外套"
    },
    {
      "word": "shorts",
      "phonetic": "",
      "meaning": "短裤"
    },
    {
      "word": "king",
      "phonetic": "",
      "meaning": "国王"
    },
    {
      "word": "want",
      "phonetic": "",
      "meaning": "想要"
    },
    {
      "word": "beautiful",
      "phonetic": "",
      "meaning": "美丽的"
    },
    {
      "word": "make",
      "phonetic": "",
      "meaning": "做"
    },
    {
      "word": "magic",
      "phonetic": "",
      "meaning": "魔法的"
    },
    {
      "word": "people",
      "phonetic": "",
      "meaning": "人们"
    },
    {
      "word": "them",
      "phonetic": "",
      "meaning": "他们"
    },
    {
      "word": "after",
      "phonetic": "",
      "meaning": "在……之后"
    },
    {
      "word": "month",
      "phonetic": "",
      "meaning": "一个月"
    },
    {
      "word": "try",
      "phonetic": "",
      "meaning": "试"
    },
    {
      "word": "try sth on",
      "phonetic": "",
      "meaning": "试穿"
    },
    {
      "word": "why",
      "phonetic": "",
      "meaning": "为什么"
    },
    {
      "word": "wonderful",
      "phonetic": "",
      "meaning": "令人惊叹的"
    },
    {
      "word": "most",
      "phonetic": "",
      "meaning": "最"
    },
    {
      "word": "any",
      "phonetic": "",
      "meaning": "任何的"
    },
    {
      "word": "or",
      "phonetic": "",
      "meaning": "或者"
    },
    {
      "word": "fox",
      "phonetic": "",
      "meaning": "狐狸"
    },
    {
      "word": "monkey",
      "phonetic": "",
      "meaning": "猴子"
    },
    {
      "word": "tell",
      "phonetic": "",
      "meaning": "告诉"
    },
    {
      "word": "truth",
      "phonetic": "",
      "meaning": "真相"
    },
    {
      "word": "wash",
      "phonetic": "",
      "meaning": "洗"
    },
    {
      "word": "hang",
      "phonetic": "",
      "meaning": "挂"
    },
    {
      "word": "hat",
      "phonetic": "",
      "meaning": "帽子"
    },
    {
      "word": "jeans",
      "phonetic": "",
      "meaning": "牛仔裤"
    },
    {
      "word": "boot",
      "phonetic": "",
      "meaning": "靴子"
    },
    {
      "word": "robe",
      "phonetic": "",
      "meaning": "长袍"
    }
  ]
}
